[
  {
    "name": "contest_delay_time",
    "type": "text",
    "label": "每题之间的时间间隔(单位秒)",
    "validation": "required"
  },
  {
    "name": "four_player_battle",
    "type": "radio",
    "options": {
      "yes": "是",
      "no": "否"
    },
    "label": "是否选择完成四人赛",
    "validation": "required"
  },
  {
    "name": "four_player_count",
    "type": "text",
    "label": "完成四人赛几次(可以选择超过两次以上)",
    "validation": "required"
  },
  {
    "label": "是否选择完成双人对战",
    "type": "radio",
    "name": "two_player_battle",
    "options": {
      "yes": "是",
      "no": "否"
    },
    "validation": "required"
  },
  {
    "name": "two_player_count",
    "type": "text",
    "label": "完成双人对战几次(可以选择超过两次以上)",
    "validation": "required"
  },
  {
    "name": "all_completed_Vibrate",
    "type": "radio",
    "options": {
      "yes": "是",
      "no": "否"
    },
    "label": "是否启用脚本运行完成后震动",
    "validation": "required",
    "help": "运行完成后设备震动半秒以提醒用户，因脚本可能定时任务执行，为避免休息时被打扰，该项默认为否"
  }
]
